pytezz/__init__.py
pytezz/EDA/DataCleaning.py
pytezz/EDA/DataVisualization.py
pytezz/EDA/__init__.py
pytezz/models/__init__.py
pytezz/models/dataloaders.py
pytezz/models/trainer.py
pytezz/models/visualize.py
pytezz-0.0.3.dist-info/METADATA
pytezz-0.0.3.dist-info/WHEEL
pytezz-0.0.3.dist-info/top_level.txt
pytezz-0.0.3.dist-info/RECORD
