Metadata-Version: 2.1
Name: pytezz
Version: 0.0.3
Summary: pytezz
Home-page: UNKNOWN
Author: daniyal shaiq
Author-email: daniyalshaiq01@gmail.com
License: UNKNOWN
Platform: linux
Platform: unix
Requires-Python: >3.5.2
Requires-Dist: torch (>=1.6.0)
